{".class":"MypyFile","_fullname":"pyarrow.__lib_pxi.config","future_import_flags":[],"is_partial_stub_package":false,"is_stub":true,"names":{".class":"SymbolTable","BuildInfo":{".class":"SymbolTableNode","kind":"Gdef","node":{".class":"TypeInfo","_promote":[],"abstract_attributes":[],"alt_promote":null,"bases":[{".class":"Instance","args":[{".class":"UnionType","items":["builtins.str",{".class":"TypeAliasType","args":[],"type_ref":"pyarrow.__lib_pxi.config.VersionInfo"}],"uses_pep604_syntax":false}],"extra_attrs":null,"type_ref":"builtins.tuple"}],"dataclass_transform_spec":null,"declared_metaclass":null,"defn":{".class":"ClassDef","fullname":"pyarrow.__lib_pxi.config.BuildInfo","name":"BuildInfo","type_vars":[]},"deletable_attributes":[],"deprecated":null,"flags":["is_named_tuple"],"fullname":"pyarrow.__lib_pxi.config.BuildInfo","has_param_spec_type":false,"metaclass_type":null,"metadata":{"namedtuple":{"fields":["version","version_info","so_version","full_so_version","compiler_id","compiler_version","compiler_flags","git_id","git_description","package_kind","build_type"]}},"module_name":"pyarrow.__lib_pxi.config","mro":["pyarrow.__lib_pxi.config.BuildInfo","builtins.tuple","typing.Sequence","typing.Reversible","typing.Collection","typing.Iterable","typing.Container","builtins.object"],"names":{".class":"SymbolTable","_NT":{".class":"SymbolTableNode","kind":"Mdef","node":{".class":"TypeVarExpr","default":{".class":"AnyType","missing_import_name":null,"source_any":null,"type_of_any":4},"fullname":"pyarrow.__lib_pxi.config.BuildInfo._NT","name":"_NT","upper_bound":{".class":"TupleType","implicit":false,"items":["builtins.str",{".class":"TypeAliasType","args":[],"type_ref":"pyarrow.__lib_pxi.config.VersionInfo"},"builtins.str","builtins.str","builtins.str","builtins.str","builtins.str","builtins.str","builtins.str","builtins.str","builtins.str"],"partial_fallback":{".class":"Instance","args":[{".class":"UnionType","items":["builtins.str",{".class":"TypeAliasType","args":[],"type_ref":"pyarrow.__lib_pxi.config.VersionInfo"}],"uses_pep604_syntax":false}],"extra_attrs":null,"type_ref":"builtins.tuple"}},"values":[],"variance":0}},"__annotations__":{".class":"SymbolTableNode","kind":"Mdef","node":{".class":"Var","flags":["is_initialized_in_class","is_ready"],"fullname":"pyarrow.__lib_pxi.config.BuildInfo.__annotations__","name":"__annotations__","setter_type":null,"type":{".class":"Instance","args":["builtins.str",{".class":"AnyType","missing_import_name":null,"source_any":null,"type_of_any":6}],"extra_attrs":null,"type_ref":"builtins.dict"}}},"__doc__":{".class":"SymbolTableNode","kind":"Mdef","node":{".class":"Var","flags":["is_initialized_in_class","is_ready"],"fullname":"pyarrow.__lib_pxi.config.BuildInfo.__doc__","name":"__doc__","setter_type":null,"type":"builtins.str"}},"__match_args__":{".class":"SymbolTableNode","kind":"Mdef","node":{".class":"Var","flags":["is_initialized_in_class","is_ready"],"fullname":"pyarrow.__lib_pxi.config.BuildInfo.__match_args__","name":"__match_args__","setter_type":null,"type":{".class":"TupleType","implicit":false,"items":[{".class":"LiteralType","fallback":"builtins.str","value":"version"},{".class":"LiteralType","fallback":"builtins.str","value":"version_info"},{".class":"LiteralType","fallback":"builtins.str","value":"so_version"},{".class":"LiteralType","fallback":"builtins.str","value":"full_so_version"},{".class":"LiteralType","fallback":"builtins.str","value":"compiler_id"},{".class":"LiteralType","fallback":"builtins.str","value":"compiler_version"},{".class":"LiteralType","fallback":"builtins.str","value":"compiler_flags"},{".class":"LiteralType","fallback":"builtins.str","value":"git_id"},{".class":"LiteralType","fallback":"builtins.str","value":"git_description"},{".class":"LiteralType","fallback":"builtins.str","value":"package_kind"},{".class":"LiteralType","fallback":"builtins.str","value":"build_type"}],"partial_fallback":{".class":"Instance","args":[{".class":"AnyType","missing_import_name":null,"source_any":null,"type_of_any":6}],"extra_attrs":null,"type_ref":"builtins.tuple"}}}},"__new__":{".class":"SymbolTableNode","kind":"Mdef","node":{".class":"FuncDef","abstract_status":0,"arg_kinds":[0,0,0,0,0,0,0,0,0,0,0,0],"arg_names":["_cls","version","version_info","so_version","full_so_version","compiler_id","compiler_version","compiler_flags","git_id","git_description","package_kind","build_type"],"dataclass_transform_spec":null,"deprecated":null,"flags":["is_static"],"fullname":"pyarrow.__lib_pxi.config.BuildInfo.__new__","name":"__new__","original_first_arg":"_cls","type":{".class":"CallableType","arg_kinds":[0,0,0,0,0,0,0,0,0,0,0,0],"arg_names":["_cls","version","version_info","so_version","full_so_version","compiler_id","compiler_version","compiler_flags","git_id","git_description","package_kind","build_type"],"arg_types":[{".class":"TypeType","is_type_form":false,"item":{".class":"TypeVarType","default":{".class":"AnyType","missing_import_name":null,"source_any":null,"type_of_any":4},"fullname":"pyarrow.__lib_pxi.config.BuildInfo._NT","id":-1,"name":"_NT","namespace":"pyarrow.__lib_pxi.config.BuildInfo.__new__","upper_bound":{".class":"TupleType","implicit":false,"items":["builtins.str",{".class":"TypeAliasType","args":[],"type_ref":"pyarrow.__lib_pxi.config.VersionInfo"},"builtins.str","builtins.str","builtins.str","builtins.str","builtins.str","builtins.str","builtins.str","builtins.str","builtins.str"],"partial_fallback":{".class":"Instance","args":[{".class":"UnionType","items":["builtins.str",{".class":"TypeAliasType","args":[],"type_ref":"pyarrow.__lib_pxi.config.VersionInfo"}],"uses_pep604_syntax":false}],"extra_attrs":null,"type_ref":"builtins.tuple"}},"values":[],"variance":0}},"builtins.str",{".class":"TypeAliasType","args":[],"type_ref":"pyarrow.__lib_pxi.config.VersionInfo"},"builtins.str","builtins.str","builtins.str","builtins.str","builtins.str","builtins.str","builtins.str","builtins.str","builtins.str"],"fallback":"builtins.function","from_concatenate":false,"implicit":false,"imprecise_arg_kinds":false,"is_bound":false,"is_ellipsis_args":false,"name":"__new__ of BuildInfo","ret_type":{".class":"TypeVarType","default":{".class":"AnyType","missing_import_name":null,"source_any":null,"type_of_any":4},"fullname":"pyarrow.__lib_pxi.config.BuildInfo._NT","id":-1,"name":"_NT","namespace":"pyarrow.__lib_pxi.config.BuildInfo.__new__","upper_bound":{".class":"TupleType","implicit":false,"items":["builtins.str",{".class":"TypeAliasType","args":[],"type_ref":"pyarrow.__lib_pxi.config.VersionInfo"},"builtins.str","builtins.str","builtins.str","builtins.str","builtins.str","builtins.str","builtins.str","builtins.str","builtins.str"],"partial_fallback":{".class":"Instance","args":[{".class":"UnionType","items":["builtins.str",{".class":"TypeAliasType","args":[],"type_ref":"pyarrow.__lib_pxi.config.VersionInfo"}],"uses_pep604_syntax":false}],"extra_attrs":null,"type_ref":"builtins.tuple"}},"values":[],"variance":0},"type_guard":null,"type_is":null,"unpack_kwargs":false,"variables":[{".class":"TypeVarType","default":{".class":"AnyType","missing_import_name":null,"source_any":null,"type_of_any":4},"fullname":"pyarrow.__lib_pxi.config.BuildInfo._NT","id":-1,"name":"_NT","namespace":"pyarrow.__lib_pxi.config.BuildInfo.__new__","upper_bound":{".class":"TupleType","implicit":false,"items":["builtins.str",{".class":"TypeAliasType","args":[],"type_ref":"pyarrow.__lib_pxi.config.VersionInfo"},"builtins.str","builtins.str","builtins.str","builtins.str","builtins.str","builtins.str","builtins.str","builtins.str","builtins.str"],"partial_fallback":{".class":"Instance","args":[{".class":"UnionType","items":["builtins.str",{".class":"TypeAliasType","args":[],"type_ref":"pyarrow.__lib_pxi.config.VersionInfo"}],"uses_pep604_syntax":false}],"extra_attrs":null,"type_ref":"builtins.tuple"}},"values":[],"variance":0}]}},"plugin_generated":true},"__replace__":{".class":"SymbolTableNode","kind":"Mdef","node":{".class":"FuncDef","abstract_status":0,"arg_kinds":[0,5,5,5,5,5,5,5,5,5,5,5],"arg_names":["_self","version","version_info","so_version","full_so_version","compiler_id","compiler_version","compiler_flags","git_id","git_description","package_kind","build_type"],"dataclass_transform_spec":null,"deprecated":null,"flags":[],"fullname":"pyarrow.__lib_pxi.config.BuildInfo.__replace__","name":"__replace__","original_first_arg":"_self","type":{".class":"CallableType","arg_kinds":[0,5,5,5,5,5,5,5,5,5,5,5],"arg_names":["_self","version","version_info","so_version","full_so_version","compiler_id","compiler_version","compiler_flags","git_id","git_description","package_kind","build_type"],"arg_types":[{".class":"TypeVarType","default":{".class":"AnyType","missing_import_name":null,"source_any":null,"type_of_any":4},"fullname":"pyarrow.__lib_pxi.config.BuildInfo._NT","id":-1,"name":"_NT","namespace":"pyarrow.__lib_pxi.config.BuildInfo.__replace__","upper_bound":{".class":"TupleType","implicit":false,"items":["builtins.str",{".class":"TypeAliasType","args":[],"type_ref":"pyarrow.__lib_pxi.config.VersionInfo"},"builtins.str","builtins.str","builtins.str","builtins.str","builtins.str","builtins.str","builtins.str","builtins.str","builtins.str"],"partial_fallback":{".class":"Instance","args":[{".class":"UnionType","items":["builtins.str",{".class":"TypeAliasType","args":[],"type_ref":"pyarrow.__lib_pxi.config.VersionInfo"}],"uses_pep604_syntax":false}],"extra_attrs":null,"type_ref":"builtins.tuple"}},"values":[],"variance":0},"builtins.str",{".class":"TypeAliasType","args":[],"type_ref":"pyarrow.__lib_pxi.config.VersionInfo"},"builtins.str","builtins.str","builtins.str","builtins.str","builtins.str","builtins.str","builtins.str","builtins.str","builtins.str"],"fallback":"builtins.function","from_concatenate":false,"implicit":false,"imprecise_arg_kinds":false,"is_bound":false,"is_ellipsis_args":false,"name":"__replace__ of BuildInfo","ret_type":{".class":"TypeVarType","default":{".class":"AnyType","missing_import_name":null,"source_any":null,"type_of_any":4},"fullname":"pyarrow.__lib_pxi.config.BuildInfo._NT","id":-1,"name":"_NT","namespace":"pyarrow.__lib_pxi.config.BuildInfo.__replace__","upper_bound":{".class":"TupleType","implicit":false,"items":["builtins.str",{".class":"TypeAliasType","args":[],"type_ref":"pyarrow.__lib_pxi.config.VersionInfo"},"builtins.str","builtins.str","builtins.str","builtins.str","builtins.str","builtins.str","builtins.str","builtins.str","builtins.str"],"partial_fallback":{".class":"Instance","args":[{".class":"UnionType","items":["builtins.str",{".class":"TypeAliasType","args":[],"type_ref":"pyarrow.__lib_pxi.config.VersionInfo"}],"uses_pep604_syntax":false}],"extra_attrs":null,"type_ref":"builtins.tuple"}},"values":[],"variance":0},"type_guard":null,"type_is":null,"unpack_kwargs":false,"variables":[{".class":"TypeVarType","default":{".class":"AnyType","missing_import_name":null,"source_any":null,"type_of_any":4},"fullname":"pyarrow.__lib_pxi.config.BuildInfo._NT","id":-1,"name":"_NT","namespace":"pyarrow.__lib_pxi.config.BuildInfo.__replace__","upper_bound":{".class":"TupleType","implicit":false,"items":["builtins.str",{".class":"TypeAliasType","args":[],"type_ref":"pyarrow.__lib_pxi.config.VersionInfo"},"builtins.str","builtins.str","builtins.str","builtins.str","builtins.str","builtins.str","builtins.str","builtins.str","builtins.str"],"partial_fallback":{".class":"Instance","args":[{".class":"UnionType","items":["builtins.str",{".class":"TypeAliasType","args":[],"type_ref":"pyarrow.__lib_pxi.config.VersionInfo"}],"uses_pep604_syntax":false}],"extra_attrs":null,"type_ref":"builtins.tuple"}},"values":[],"variance":0}]}},"plugin_generated":true},"_asdict":{".class":"SymbolTableNode","kind":"Mdef","node":{".class":"FuncDef","abstract_status":0,"arg_kinds":[0],"arg_names":["_self"],"dataclass_transform_spec":null,"deprecated":null,"flags":[],"fullname":"pyarrow.__lib_pxi.config.BuildInfo._asdict","name":"_asdict","original_first_arg":"_self","type":{".class":"CallableType","arg_kinds":[0],"arg_names":["_self"],"arg_types":[{".class":"TypeVarType","default":{".class":"AnyType","missing_import_name":null,"source_any":null,"type_of_any":4},"fullname":"pyarrow.__lib_pxi.config.BuildInfo._NT","id":-1,"name":"_NT","namespace":"pyarrow.__lib_pxi.config.BuildInfo._asdict","upper_bound":{".class":"TupleType","implicit":false,"items":["builtins.str",{".class":"TypeAliasType","args":[],"type_ref":"pyarrow.__lib_pxi.config.VersionInfo"},"builtins.str","builtins.str","builtins.str","builtins.str","builtins.str","builtins.str","builtins.str","builtins.str","builtins.str"],"partial_fallback":{".class":"Instance","args":[{".class":"UnionType","items":["builtins.str",{".class":"TypeAliasType","args":[],"type_ref":"pyarrow.__lib_pxi.config.VersionInfo"}],"uses_pep604_syntax":false}],"extra_attrs":null,"type_ref":"builtins.tuple"}},"values":[],"variance":0}],"fallback":"builtins.function","from_concatenate":false,"implicit":false,"imprecise_arg_kinds":false,"is_bound":false,"is_ellipsis_args":false,"name":"_asdict of BuildInfo","ret_type":{".class":"Instance","args":["builtins.str",{".class":"AnyType","missing_import_name":null,"source_any":null,"type_of_any":6}],"extra_attrs":null,"type_ref":"builtins.dict"},"type_guard":null,"type_is":null,"unpack_kwargs":false,"variables":[{".class":"TypeVarType","default":{".class":"AnyType","missing_import_name":null,"source_any":null,"type_of_any":4},"fullname":"pyarrow.__lib_pxi.config.BuildInfo._NT","id":-1,"name":"_NT","namespace":"pyarrow.__lib_pxi.config.BuildInfo._asdict","upper_bound":{".class":"TupleType","implicit":false,"items":["builtins.str",{".class":"TypeAliasType","args":[],"type_ref":"pyarrow.__lib_pxi.config.VersionInfo"},"builtins.str","builtins.str","builtins.str","builtins.str","builtins.str","builtins.str","builtins.str","builtins.str","builtins.str"],"partial_fallback":{".class":"Instance","args":[{".class":"UnionType","items":["builtins.str",{".class":"TypeAliasType","args":[],"type_ref":"pyarrow.__lib_pxi.config.VersionInfo"}],"uses_pep604_syntax":false}],"extra_attrs":null,"type_ref":"builtins.tuple"}},"values":[],"variance":0}]}},"plugin_generated":true},"_field_defaults":{".class":"SymbolTableNode","kind":"Mdef","node":{".class":"Var","flags":["is_initialized_in_class","is_ready"],"fullname":"pyarrow.__lib_pxi.config.BuildInfo._field_defaults","name":"_field_defaults","setter_type":null,"type":{".class":"Instance","args":["builtins.str",{".class":"AnyType","missing_import_name":null,"source_any":null,"type_of_any":6}],"extra_attrs":null,"type_ref":"builtins.dict"}}},"_field_types":{".class":"SymbolTableNode","kind":"Mdef","node":{".class":"Var","flags":["is_initialized_in_class","is_ready"],"fullname":"pyarrow.__lib_pxi.config.BuildInfo._field_types","name":"_field_types","setter_type":null,"type":{".class":"Instance","args":["builtins.str",{".class":"AnyType","missing_import_name":null,"source_any":null,"type_of_any":6}],"extra_attrs":null,"type_ref":"builtins.dict"}}},"_fields":{".class":"SymbolTableNode","kind":"Mdef","node":{".class":"Var","flags":["is_initialized_in_class","is_ready"],"fullname":"pyarrow.__lib_pxi.config.BuildInfo._fields","name":"_fields","setter_type":null,"type":{".class":"TupleType","implicit":false,"items":["builtins.str","builtins.str","builtins.str","builtins.str","builtins.str","builtins.str","builtins.str","builtins.str","builtins.str","builtins.str","builtins.str"],"partial_fallback":{".class":"Instance","args":[{".class":"AnyType","missing_import_name":null,"source_any":null,"type_of_any":6}],"extra_attrs":null,"type_ref":"builtins.tuple"}}}},"_make":{".class":"SymbolTableNode","kind":"Mdef","node":{".class":"Decorator","func":{".class":"FuncDef","abstract_status":0,"arg_kinds":[0,0],"arg_names":["_cls","iterable"],"dataclass_transform_spec":null,"deprecated":null,"flags":["is_class","is_decorated"],"fullname":"pyarrow.__lib_pxi.config.BuildInfo._make","name":"_make","original_first_arg":"_cls","type":{".class":"CallableType","arg_kinds":[0,0],"arg_names":["_cls","iterable"],"arg_types":[{".class":"TypeType","is_type_form":false,"item":{".class":"TypeVarType","default":{".class":"AnyType","missing_import_name":null,"source_any":null,"type_of_any":4},"fullname":"pyarrow.__lib_pxi.config.BuildInfo._NT","id":-1,"name":"_NT","namespace":"pyarrow.__lib_pxi.config.BuildInfo._make","upper_bound":{".class":"TupleType","implicit":false,"items":["builtins.str",{".class":"TypeAliasType","args":[],"type_ref":"pyarrow.__lib_pxi.config.VersionInfo"},"builtins.str","builtins.str","builtins.str","builtins.str","builtins.str","builtins.str","builtins.str","builtins.str","builtins.str"],"partial_fallback":{".class":"Instance","args":[{".class":"UnionType","items":["builtins.str",{".class":"TypeAliasType","args":[],"type_ref":"pyarrow.__lib_pxi.config.VersionInfo"}],"uses_pep604_syntax":false}],"extra_attrs":null,"type_ref":"builtins.tuple"}},"values":[],"variance":0}},{".class":"Instance","args":[{".class":"AnyType","missing_import_name":null,"source_any":null,"type_of_any":6}],"extra_attrs":null,"type_ref":"typing.Iterable"}],"fallback":"builtins.function","from_concatenate":false,"implicit":false,"imprecise_arg_kinds":false,"is_bound":false,"is_ellipsis_args":false,"name":"_make of BuildInfo","ret_type":{".class":"TypeVarType","default":{".class":"AnyType","missing_import_name":null,"source_any":null,"type_of_any":4},"fullname":"pyarrow.__lib_pxi.config.BuildInfo._NT","id":-1,"name":"_NT","namespace":"pyarrow.__lib_pxi.config.BuildInfo._make","upper_bound":{".class":"TupleType","implicit":false,"items":["builtins.str",{".class":"TypeAliasType","args":[],"type_ref":"pyarrow.__lib_pxi.config.VersionInfo"},"builtins.str","builtins.str","builtins.str","builtins.str","builtins.str","builtins.str","builtins.str","builtins.str","builtins.str"],"partial_fallback":{".class":"Instance","args":[{".class":"UnionType","items":["builtins.str",{".class":"TypeAliasType","args":[],"type_ref":"pyarrow.__lib_pxi.config.VersionInfo"}],"uses_pep604_syntax":false}],"extra_attrs":null,"type_ref":"builtins.tuple"}},"values":[],"variance":0},"type_guard":null,"type_is":null,"unpack_kwargs":false,"variables":[{".class":"TypeVarType","default":{".class":"AnyType","missing_import_name":null,"source_any":null,"type_of_any":4},"fullname":"pyarrow.__lib_pxi.config.BuildInfo._NT","id":-1,"name":"_NT","namespace":"pyarrow.__lib_pxi.config.BuildInfo._make","upper_bound":{".class":"TupleType","implicit":false,"items":["builtins.str",{".class":"TypeAliasType","args":[],"type_ref":"pyarrow.__lib_pxi.config.VersionInfo"},"builtins.str","builtins.str","builtins.str","builtins.str","builtins.str","builtins.str","builtins.str","builtins.str","builtins.str"],"partial_fallback":{".class":"Instance","args":[{".class":"UnionType","items":["builtins.str",{".class":"TypeAliasType","args":[],"type_ref":"pyarrow.__lib_pxi.config.VersionInfo"}],"uses_pep604_syntax":false}],"extra_attrs":null,"type_ref":"builtins.tuple"}},"values":[],"variance":0}]}},"is_overload":false,"var":{".class":"Var","flags":["is_classmethod","is_ready"],"fullname":"pyarrow.__lib_pxi.config.BuildInfo._make","name":"_make","setter_type":null,"type":{".class":"CallableType","arg_kinds":[0,0],"arg_names":["_cls","iterable"],"arg_types":[{".class":"TypeType","is_type_form":false,"item":{".class":"TypeVarType","default":{".class":"AnyType","missing_import_name":null,"source_any":null,"type_of_any":4},"fullname":"pyarrow.__lib_pxi.config.BuildInfo._NT","id":-1,"name":"_NT","namespace":"pyarrow.__lib_pxi.config.BuildInfo._make","upper_bound":{".class":"TupleType","implicit":false,"items":["builtins.str",{".class":"TypeAliasType","args":[],"type_ref":"pyarrow.__lib_pxi.config.VersionInfo"},"builtins.str","builtins.str","builtins.str","builtins.str","builtins.str","builtins.str","builtins.str","builtins.str","builtins.str"],"partial_fallback":{".class":"Instance","args":[{".class":"UnionType","items":["builtins.str",{".class":"TypeAliasType","args":[],"type_ref":"pyarrow.__lib_pxi.config.VersionInfo"}],"uses_pep604_syntax":false}],"extra_attrs":null,"type_ref":"builtins.tuple"}},"values":[],"variance":0}},{".class":"Instance","args":[{".class":"AnyType","missing_import_name":null,"source_any":null,"type_of_any":6}],"extra_attrs":null,"type_ref":"typing.Iterable"}],"fallback":"builtins.function","from_concatenate":false,"implicit":false,"imprecise_arg_kinds":false,"is_bound":false,"is_ellipsis_args":false,"name":"_make of BuildInfo","ret_type":{".class":"TypeVarType","default":{".class":"AnyType","missing_import_name":null,"source_any":null,"type_of_any":4},"fullname":"pyarrow.__lib_pxi.config.BuildInfo._NT","id":-1,"name":"_NT","namespace":"pyarrow.__lib_pxi.config.BuildInfo._make","upper_bound":{".class":"TupleType","implicit":false,"items":["builtins.str",{".class":"TypeAliasType","args":[],"type_ref":"pyarrow.__lib_pxi.config.VersionInfo"},"builtins.str","builtins.str","builtins.str","builtins.str","builtins.str","builtins.str","builtins.str","builtins.str","builtins.str"],"partial_fallback":{".class":"Instance","args":[{".class":"UnionType","items":["builtins.str",{".class":"TypeAliasType","args":[],"type_ref":"pyarrow.__lib_pxi.config.VersionInfo"}],"uses_pep604_syntax":false}],"extra_attrs":null,"type_ref":"builtins.tuple"}},"values":[],"variance":0},"type_guard":null,"type_is":null,"unpack_kwargs":false,"variables":[{".class":"TypeVarType","default":{".class":"AnyType","missing_import_name":null,"source_any":null,"type_of_any":4},"fullname":"pyarrow.__lib_pxi.config.BuildInfo._NT","id":-1,"name":"_NT","namespace":"pyarrow.__lib_pxi.config.BuildInfo._make","upper_bound":{".class":"TupleType","implicit":false,"items":["builtins.str",{".class":"TypeAliasType","args":[],"type_ref":"pyarrow.__lib_pxi.config.VersionInfo"},"builtins.str","builtins.str","builtins.str","builtins.str","builtins.str","builtins.str","builtins.str","builtins.str","builtins.str"],"partial_fallback":{".class":"Instance","args":[{".class":"UnionType","items":["builtins.str",{".class":"TypeAliasType","args":[],"type_ref":"pyarrow.__lib_pxi.config.VersionInfo"}],"uses_pep604_syntax":false}],"extra_attrs":null,"type_ref":"builtins.tuple"}},"values":[],"variance":0}]}}},"plugin_generated":true},"_replace":{".class":"SymbolTableNode","kind":"Mdef","node":{".class":"FuncDef","abstract_status":0,"arg_kinds":[0,5,5,5,5,5,5,5,5,5,5,5],"arg_names":["_self","version","version_info","so_version","full_so_version","compiler_id","compiler_version","compiler_flags","git_id","git_description","package_kind","build_type"],"dataclass_transform_spec":null,"deprecated":null,"flags":[],"fullname":"pyarrow.__lib_pxi.config.BuildInfo._replace","name":"_replace","original_first_arg":"_self","type":{".class":"CallableType","arg_kinds":[0,5,5,5,5,5,5,5,5,5,5,5],"arg_names":["_self","version","version_info","so_version","full_so_version","compiler_id","compiler_version","compiler_flags","git_id","git_description","package_kind","build_type"],"arg_types":[{".class":"TypeVarType","default":{".class":"AnyType","missing_import_name":null,"source_any":null,"type_of_any":4},"fullname":"pyarrow.__lib_pxi.config.BuildInfo._NT","id":-1,"name":"_NT","namespace":"pyarrow.__lib_pxi.config.BuildInfo._replace","upper_bound":{".class":"TupleType","implicit":false,"items":["builtins.str",{".class":"TypeAliasType","args":[],"type_ref":"pyarrow.__lib_pxi.config.VersionInfo"},"builtins.str","builtins.str","builtins.str","builtins.str","builtins.str","builtins.str","builtins.str","builtins.str","builtins.str"],"partial_fallback":{".class":"Instance","args":[{".class":"UnionType","items":["builtins.str",{".class":"TypeAliasType","args":[],"type_ref":"pyarrow.__lib_pxi.config.VersionInfo"}],"uses_pep604_syntax":false}],"extra_attrs":null,"type_ref":"builtins.tuple"}},"values":[],"variance":0},"builtins.str",{".class":"TypeAliasType","args":[],"type_ref":"pyarrow.__lib_pxi.config.VersionInfo"},"builtins.str","builtins.str","builtins.str","builtins.str","builtins.str","builtins.str","builtins.str","builtins.str","builtins.str"],"fallback":"builtins.function","from_concatenate":false,"implicit":false,"imprecise_arg_kinds":false,"is_bound":false,"is_ellipsis_args":false,"name":"_replace of BuildInfo","ret_type":{".class":"TypeVarType","default":{".class":"AnyType","missing_import_name":null,"source_any":null,"type_of_any":4},"fullname":"pyarrow.__lib_pxi.config.BuildInfo._NT","id":-1,"name":"_NT","namespace":"pyarrow.__lib_pxi.config.BuildInfo._replace","upper_bound":{".class":"TupleType","implicit":false,"items":["builtins.str",{".class":"TypeAliasType","args":[],"type_ref":"pyarrow.__lib_pxi.config.VersionInfo"},"builtins.str","builtins.str","builtins.str","builtins.str","builtins.str","builtins.str","builtins.str","builtins.str","builtins.str"],"partial_fallback":{".class":"Instance","args":[{".class":"UnionType","items":["builtins.str",{".class":"TypeAliasType","args":[],"type_ref":"pyarrow.__lib_pxi.config.VersionInfo"}],"uses_pep604_syntax":false}],"extra_attrs":null,"type_ref":"builtins.tuple"}},"values":[],"variance":0},"type_guard":null,"type_is":null,"unpack_kwargs":false,"variables":[{".class":"TypeVarType","default":{".class":"AnyType","missing_import_name":null,"source_any":null,"type_of_any":4},"fullname":"pyarrow.__lib_pxi.config.BuildInfo._NT","id":-1,"name":"_NT","namespace":"pyarrow.__lib_pxi.config.BuildInfo._replace","upper_bound":{".class":"TupleType","implicit":false,"items":["builtins.str",{".class":"TypeAliasType","args":[],"type_ref":"pyarrow.__lib_pxi.config.VersionInfo"},"builtins.str","builtins.str","builtins.str","builtins.str","builtins.str","builtins.str","builtins.str","builtins.str","builtins.str"],"partial_fallback":{".class":"Instance","args":[{".class":"UnionType","items":["builtins.str",{".class":"TypeAliasType","args":[],"type_ref":"pyarrow.__lib_pxi.config.VersionInfo"}],"uses_pep604_syntax":false}],"extra_attrs":null,"type_ref":"builtins.tuple"}},"values":[],"variance":0}]}},"plugin_generated":true},"_source":{".class":"SymbolTableNode","kind":"Mdef","node":{".class":"Var","flags":["is_initialized_in_class","is_ready"],"fullname":"pyarrow.__lib_pxi.config.BuildInfo._source","name":"_source","setter_type":null,"type":"builtins.str"}},"build_type":{".class":"SymbolTableNode","kind":"Mdef","node":{".class":"Var","flags":["is_property","is_ready"],"fullname":"pyarrow.__lib_pxi.config.BuildInfo.build_type","name":"build_type","setter_type":null,"type":"builtins.str"}},"build_type-redefinition":{".class":"SymbolTableNode","cross_ref":"pyarrow.__lib_pxi.config.BuildInfo.build_type","kind":"Mdef"},"compiler_flags":{".class":"SymbolTableNode","kind":"Mdef","node":{".class":"Var","flags":["is_property","is_ready"],"fullname":"pyarrow.__lib_pxi.config.BuildInfo.compiler_flags","name":"compiler_flags","setter_type":null,"type":"builtins.str"}},"compiler_flags-redefinition":{".class":"SymbolTableNode","cross_ref":"pyarrow.__lib_pxi.config.BuildInfo.compiler_flags","kind":"Mdef"},"compiler_id":{".class":"SymbolTableNode","kind":"Mdef","node":{".class":"Var","flags":["is_property","is_ready"],"fullname":"pyarrow.__lib_pxi.config.BuildInfo.compiler_id","name":"compiler_id","setter_type":null,"type":"builtins.str"}},"compiler_id-redefinition":{".class":"SymbolTableNode","cross_ref":"pyarrow.__lib_pxi.config.BuildInfo.compiler_id","kind":"Mdef"},"compiler_version":{".class":"SymbolTableNode","kind":"Mdef","node":{".class":"Var","flags":["is_property","is_ready"],"fullname":"pyarrow.__lib_pxi.config.BuildInfo.compiler_version","name":"compiler_version","setter_type":null,"type":"builtins.str"}},"compiler_version-redefinition":{".class":"SymbolTableNode","cross_ref":"pyarrow.__lib_pxi.config.BuildInfo.compiler_version","kind":"Mdef"},"full_so_version":{".class":"SymbolTableNode","kind":"Mdef","node":{".class":"Var","flags":["is_property","is_ready"],"fullname":"pyarrow.__lib_pxi.config.BuildInfo.full_so_version","name":"full_so_version","setter_type":null,"type":"builtins.str"}},"full_so_version-redefinition":{".class":"SymbolTableNode","cross_ref":"pyarrow.__lib_pxi.config.BuildInfo.full_so_version","kind":"Mdef"},"git_description":{".class":"SymbolTableNode","kind":"Mdef","node":{".class":"Var","flags":["is_property","is_ready"],"fullname":"pyarrow.__lib_pxi.config.BuildInfo.git_description","name":"git_description","setter_type":null,"type":"builtins.str"}},"git_description-redefinition":{".class":"SymbolTableNode","cross_ref":"pyarrow.__lib_pxi.config.BuildInfo.git_description","kind":"Mdef"},"git_id":{".class":"SymbolTableNode","kind":"Mdef","node":{".class":"Var","flags":["is_property","is_ready"],"fullname":"pyarrow.__lib_pxi.config.BuildInfo.git_id","name":"git_id","setter_type":null,"type":"builtins.str"}},"git_id-redefinition":{".class":"SymbolTableNode","cross_ref":"pyarrow.__lib_pxi.config.BuildInfo.git_id","kind":"Mdef"},"package_kind":{".class":"SymbolTableNode","kind":"Mdef","node":{".class":"Var","flags":["is_property","is_ready"],"fullname":"pyarrow.__lib_pxi.config.BuildInfo.package_kind","name":"package_kind","setter_type":null,"type":"builtins.str"}},"package_kind-redefinition":{".class":"SymbolTableNode","cross_ref":"pyarrow.__lib_pxi.config.BuildInfo.package_kind","kind":"Mdef"},"so_version":{".class":"SymbolTableNode","kind":"Mdef","node":{".class":"Var","flags":["is_property","is_ready"],"fullname":"pyarrow.__lib_pxi.config.BuildInfo.so_version","name":"so_version","setter_type":null,"type":"builtins.str"}},"so_version-redefinition":{".class":"SymbolTableNode","cross_ref":"pyarrow.__lib_pxi.config.BuildInfo.so_version","kind":"Mdef"},"version":{".class":"SymbolTableNode","kind":"Mdef","node":{".class":"Var","flags":["is_property","is_ready"],"fullname":"pyarrow.__lib_pxi.config.BuildInfo.version","name":"version","setter_type":null,"type":"builtins.str"}},"version-redefinition":{".class":"SymbolTableNode","cross_ref":"pyarrow.__lib_pxi.config.BuildInfo.version","kind":"Mdef"},"version_info":{".class":"SymbolTableNode","kind":"Mdef","node":{".class":"Var","flags":["is_property","is_ready"],"fullname":"pyarrow.__lib_pxi.config.BuildInfo.version_info","name":"version_info","setter_type":null,"type":{".class":"TypeAliasType","args":[],"type_ref":"pyarrow.__lib_pxi.config.VersionInfo"}}},"version_info-redefinition":{".class":"SymbolTableNode","cross_ref":"pyarrow.__lib_pxi.config.BuildInfo.version_info","kind":"Mdef"}},"self_type":{".class":"TypeVarType","default":{".class":"AnyType","missing_import_name":null,"source_any":null,"type_of_any":4},"fullname":"pyarrow.__lib_pxi.config.BuildInfo.Self","id":0,"name":"Self","namespace":"","upper_bound":{".class":"TupleType","implicit":false,"items":["builtins.str",{".class":"TypeAliasType","args":[],"type_ref":"pyarrow.__lib_pxi.config.VersionInfo"},"builtins.str","builtins.str","builtins.str","builtins.str","builtins.str","builtins.str","builtins.str","builtins.str","builtins.str"],"partial_fallback":"pyarrow.__lib_pxi.config.BuildInfo"},"values":[],"variance":0},"slots":null,"tuple_type":{".class":"TupleType","implicit":false,"items":["builtins.str",{".class":"TypeAliasType","args":[],"type_ref":"pyarrow.__lib_pxi.config.VersionInfo"},"builtins.str","builtins.str","builtins.str","builtins.str","builtins.str","builtins.str","builtins.str","builtins.str","builtins.str"],"partial_fallback":{".class":"Instance","args":[{".class":"UnionType","items":["builtins.str",{".class":"TypeAliasType","args":[],"type_ref":"pyarrow.__lib_pxi.config.VersionInfo"}],"uses_pep604_syntax":false}],"extra_attrs":null,"type_ref":"builtins.tuple"}},"type_vars":[],"typeddict_type":null}},"NamedTuple":{".class":"SymbolTableNode","cross_ref":"typing.NamedTuple","kind":"Gdef","module_hidden":true,"module_public":false},"RuntimeInfo":{".class":"SymbolTableNode","kind":"Gdef","node":{".class":"TypeInfo","_promote":[],"abstract_attributes":[],"alt_promote":null,"bases":[{".class":"Instance","args":["builtins.str"],"extra_attrs":null,"type_ref":"builtins.tuple"}],"dataclass_transform_spec":null,"declared_metaclass":null,"defn":{".class":"ClassDef","fullname":"pyarrow.__lib_pxi.config.RuntimeInfo","name":"RuntimeInfo","type_vars":[]},"deletable_attributes":[],"deprecated":null,"flags":["is_named_tuple"],"fullname":"pyarrow.__lib_pxi.config.RuntimeInfo","has_param_spec_type":false,"metaclass_type":null,"metadata":{"namedtuple":{"fields":["simd_level","detected_simd_level"]}},"module_name":"pyarrow.__lib_pxi.config","mro":["pyarrow.__lib_pxi.config.RuntimeInfo","builtins.tuple","typing.Sequence","typing.Reversible","typing.Collection","typing.Iterable","typing.Container","builtins.object"],"names":{".class":"SymbolTable","_NT":{".class":"SymbolTableNode","kind":"Mdef","node":{".class":"TypeVarExpr","default":{".class":"AnyType","missing_import_name":null,"source_any":null,"type_of_any":4},"fullname":"pyarrow.__lib_pxi.config.RuntimeInfo._NT","name":"_NT","upper_bound":{".class":"TupleType","implicit":false,"items":["builtins.str","builtins.str"],"partial_fallback":{".class":"Instance","args":["builtins.str"],"extra_attrs":null,"type_ref":"builtins.tuple"}},"values":[],"variance":0}},"__annotations__":{".class":"SymbolTableNode","kind":"Mdef","node":{".class":"Var","flags":["is_initialized_in_class","is_ready"],"fullname":"pyarrow.__lib_pxi.config.RuntimeInfo.__annotations__","name":"__annotations__","setter_type":null,"type":{".class":"Instance","args":["builtins.str",{".class":"AnyType","missing_import_name":null,"source_any":null,"type_of_any":6}],"extra_attrs":null,"type_ref":"builtins.dict"}}},"__doc__":{".class":"SymbolTableNode","kind":"Mdef","node":{".class":"Var","flags":["is_initialized_in_class","is_ready"],"fullname":"pyarrow.__lib_pxi.config.RuntimeInfo.__doc__","name":"__doc__","setter_type":null,"type":"builtins.str"}},"__match_args__":{".class":"SymbolTableNode","kind":"Mdef","node":{".class":"Var","flags":["is_initialized_in_class","is_ready"],"fullname":"pyarrow.__lib_pxi.config.RuntimeInfo.__match_args__","name":"__match_args__","setter_type":null,"type":{".class":"TupleType","implicit":false,"items":[{".class":"LiteralType","fallback":"builtins.str","value":"simd_level"},{".class":"LiteralType","fallback":"builtins.str","value":"detected_simd_level"}],"partial_fallback":{".class":"Instance","args":[{".class":"AnyType","missing_import_name":null,"source_any":null,"type_of_any":6}],"extra_attrs":null,"type_ref":"builtins.tuple"}}}},"__new__":{".class":"SymbolTableNode","kind":"Mdef","node":{".class":"FuncDef","abstract_status":0,"arg_kinds":[0,0,0],"arg_names":["_cls","simd_level","detected_simd_level"],"dataclass_transform_spec":null,"deprecated":null,"flags":["is_static"],"fullname":"pyarrow.__lib_pxi.config.RuntimeInfo.__new__","name":"__new__","original_first_arg":"_cls","type":{".class":"CallableType","arg_kinds":[0,0,0],"arg_names":["_cls","simd_level","detected_simd_level"],"arg_types":[{".class":"TypeType","is_type_form":false,"item":{".class":"TypeVarType","default":{".class":"AnyType","missing_import_name":null,"source_any":null,"type_of_any":4},"fullname":"pyarrow.__lib_pxi.config.RuntimeInfo._NT","id":-1,"name":"_NT","namespace":"pyarrow.__lib_pxi.config.RuntimeInfo.__new__","upper_bound":{".class":"TupleType","implicit":false,"items":["builtins.str","builtins.str"],"partial_fallback":{".class":"Instance","args":["builtins.str"],"extra_attrs":null,"type_ref":"builtins.tuple"}},"values":[],"variance":0}},"builtins.str","builtins.str"],"fallback":"builtins.function","from_concatenate":false,"implicit":false,"imprecise_arg_kinds":false,"is_bound":false,"is_ellipsis_args":false,"name":"__new__ of RuntimeInfo","ret_type":{".class":"TypeVarType","default":{".class":"AnyType","missing_import_name":null,"source_any":null,"type_of_any":4},"fullname":"pyarrow.__lib_pxi.config.RuntimeInfo._NT","id":-1,"name":"_NT","namespace":"pyarrow.__lib_pxi.config.RuntimeInfo.__new__","upper_bound":{".class":"TupleType","implicit":false,"items":["builtins.str","builtins.str"],"partial_fallback":{".class":"Instance","args":["builtins.str"],"extra_attrs":null,"type_ref":"builtins.tuple"}},"values":[],"variance":0},"type_guard":null,"type_is":null,"unpack_kwargs":false,"variables":[{".class":"TypeVarType","default":{".class":"AnyType","missing_import_name":null,"source_any":null,"type_of_any":4},"fullname":"pyarrow.__lib_pxi.config.RuntimeInfo._NT","id":-1,"name":"_NT","namespace":"pyarrow.__lib_pxi.config.RuntimeInfo.__new__","upper_bound":{".class":"TupleType","implicit":false,"items":["builtins.str","builtins.str"],"partial_fallback":{".class":"Instance","args":["builtins.str"],"extra_attrs":null,"type_ref":"builtins.tuple"}},"values":[],"variance":0}]}},"plugin_generated":true},"__replace__":{".class":"SymbolTableNode","kind":"Mdef","node":{".class":"FuncDef","abstract_status":0,"arg_kinds":[0,5,5],"arg_names":["_self","simd_level","detected_simd_level"],"dataclass_transform_spec":null,"deprecated":null,"flags":[],"fullname":"pyarrow.__lib_pxi.config.RuntimeInfo.__replace__","name":"__replace__","original_first_arg":"_self","type":{".class":"CallableType","arg_kinds":[0,5,5],"arg_names":["_self","simd_level","detected_simd_level"],"arg_types":[{".class":"TypeVarType","default":{".class":"AnyType","missing_import_name":null,"source_any":null,"type_of_any":4},"fullname":"pyarrow.__lib_pxi.config.RuntimeInfo._NT","id":-1,"name":"_NT","namespace":"pyarrow.__lib_pxi.config.RuntimeInfo.__replace__","upper_bound":{".class":"TupleType","implicit":false,"items":["builtins.str","builtins.str"],"partial_fallback":{".class":"Instance","args":["builtins.str"],"extra_attrs":null,"type_ref":"builtins.tuple"}},"values":[],"variance":0},"builtins.str","builtins.str"],"fallback":"builtins.function","from_concatenate":false,"implicit":false,"imprecise_arg_kinds":false,"is_bound":false,"is_ellipsis_args":false,"name":"__replace__ of RuntimeInfo","ret_type":{".class":"TypeVarType","default":{".class":"AnyType","missing_import_name":null,"source_any":null,"type_of_any":4},"fullname":"pyarrow.__lib_pxi.config.RuntimeInfo._NT","id":-1,"name":"_NT","namespace":"pyarrow.__lib_pxi.config.RuntimeInfo.__replace__","upper_bound":{".class":"TupleType","implicit":false,"items":["builtins.str","builtins.str"],"partial_fallback":{".class":"Instance","args":["builtins.str"],"extra_attrs":null,"type_ref":"builtins.tuple"}},"values":[],"variance":0},"type_guard":null,"type_is":null,"unpack_kwargs":false,"variables":[{".class":"TypeVarType","default":{".class":"AnyType","missing_import_name":null,"source_any":null,"type_of_any":4},"fullname":"pyarrow.__lib_pxi.config.RuntimeInfo._NT","id":-1,"name":"_NT","namespace":"pyarrow.__lib_pxi.config.RuntimeInfo.__replace__","upper_bound":{".class":"TupleType","implicit":false,"items":["builtins.str","builtins.str"],"partial_fallback":{".class":"Instance","args":["builtins.str"],"extra_attrs":null,"type_ref":"builtins.tuple"}},"values":[],"variance":0}]}},"plugin_generated":true},"_asdict":{".class":"SymbolTableNode","kind":"Mdef","node":{".class":"FuncDef","abstract_status":0,"arg_kinds":[0],"arg_names":["_self"],"dataclass_transform_spec":null,"deprecated":null,"flags":[],"fullname":"pyarrow.__lib_pxi.config.RuntimeInfo._asdict","name":"_asdict","original_first_arg":"_self","type":{".class":"CallableType","arg_kinds":[0],"arg_names":["_self"],"arg_types":[{".class":"TypeVarType","default":{".class":"AnyType","missing_import_name":null,"source_any":null,"type_of_any":4},"fullname":"pyarrow.__lib_pxi.config.RuntimeInfo._NT","id":-1,"name":"_NT","namespace":"pyarrow.__lib_pxi.config.RuntimeInfo._asdict","upper_bound":{".class":"TupleType","implicit":false,"items":["builtins.str","builtins.str"],"partial_fallback":{".class":"Instance","args":["builtins.str"],"extra_attrs":null,"type_ref":"builtins.tuple"}},"values":[],"variance":0}],"fallback":"builtins.function","from_concatenate":false,"implicit":false,"imprecise_arg_kinds":false,"is_bound":false,"is_ellipsis_args":false,"name":"_asdict of RuntimeInfo","ret_type":{".class":"Instance","args":["builtins.str",{".class":"AnyType","missing_import_name":null,"source_any":null,"type_of_any":6}],"extra_attrs":null,"type_ref":"builtins.dict"},"type_guard":null,"type_is":null,"unpack_kwargs":false,"variables":[{".class":"TypeVarType","default":{".class":"AnyType","missing_import_name":null,"source_any":null,"type_of_any":4},"fullname":"pyarrow.__lib_pxi.config.RuntimeInfo._NT","id":-1,"name":"_NT","namespace":"pyarrow.__lib_pxi.config.RuntimeInfo._asdict","upper_bound":{".class":"TupleType","implicit":false,"items":["builtins.str","builtins.str"],"partial_fallback":{".class":"Instance","args":["builtins.str"],"extra_attrs":null,"type_ref":"builtins.tuple"}},"values":[],"variance":0}]}},"plugin_generated":true},"_field_defaults":{".class":"SymbolTableNode","kind":"Mdef","node":{".class":"Var","flags":["is_initialized_in_class","is_ready"],"fullname":"pyarrow.__lib_pxi.config.RuntimeInfo._field_defaults","name":"_field_defaults","setter_type":null,"type":{".class":"Instance","args":["builtins.str",{".class":"AnyType","missing_import_name":null,"source_any":null,"type_of_any":6}],"extra_attrs":null,"type_ref":"builtins.dict"}}},"_field_types":{".class":"SymbolTableNode","kind":"Mdef","node":{".class":"Var","flags":["is_initialized_in_class","is_ready"],"fullname":"pyarrow.__lib_pxi.config.RuntimeInfo._field_types","name":"_field_types","setter_type":null,"type":{".class":"Instance","args":["builtins.str",{".class":"AnyType","missing_import_name":null,"source_any":null,"type_of_any":6}],"extra_attrs":null,"type_ref":"builtins.dict"}}},"_fields":{".class":"SymbolTableNode","kind":"Mdef","node":{".class":"Var","flags":["is_initialized_in_class","is_ready"],"fullname":"pyarrow.__lib_pxi.config.RuntimeInfo._fields","name":"_fields","setter_type":null,"type":{".class":"TupleType","implicit":false,"items":["builtins.str","builtins.str"],"partial_fallback":{".class":"Instance","args":[{".class":"AnyType","missing_import_name":null,"source_any":null,"type_of_any":6}],"extra_attrs":null,"type_ref":"builtins.tuple"}}}},"_make":{".class":"SymbolTableNode","kind":"Mdef","node":{".class":"Decorator","func":{".class":"FuncDef","abstract_status":0,"arg_kinds":[0,0],"arg_names":["_cls","iterable"],"dataclass_transform_spec":null,"deprecated":null,"flags":["is_class","is_decorated"],"fullname":"pyarrow.__lib_pxi.config.RuntimeInfo._make","name":"_make","original_first_arg":"_cls","type":{".class":"CallableType","arg_kinds":[0,0],"arg_names":["_cls","iterable"],"arg_types":[{".class":"TypeType","is_type_form":false,"item":{".class":"TypeVarType","default":{".class":"AnyType","missing_import_name":null,"source_any":null,"type_of_any":4},"fullname":"pyarrow.__lib_pxi.config.RuntimeInfo._NT","id":-1,"name":"_NT","namespace":"pyarrow.__lib_pxi.config.RuntimeInfo._make","upper_bound":{".class":"TupleType","implicit":false,"items":["builtins.str","builtins.str"],"partial_fallback":{".class":"Instance","args":["builtins.str"],"extra_attrs":null,"type_ref":"builtins.tuple"}},"values":[],"variance":0}},{".class":"Instance","args":[{".class":"AnyType","missing_import_name":null,"source_any":null,"type_of_any":6}],"extra_attrs":null,"type_ref":"typing.Iterable"}],"fallback":"builtins.function","from_concatenate":false,"implicit":false,"imprecise_arg_kinds":false,"is_bound":false,"is_ellipsis_args":false,"name":"_make of RuntimeInfo","ret_type":{".class":"TypeVarType","default":{".class":"AnyType","missing_import_name":null,"source_any":null,"type_of_any":4},"fullname":"pyarrow.__lib_pxi.config.RuntimeInfo._NT","id":-1,"name":"_NT","namespace":"pyarrow.__lib_pxi.config.RuntimeInfo._make","upper_bound":{".class":"TupleType","implicit":false,"items":["builtins.str","builtins.str"],"partial_fallback":{".class":"Instance","args":["builtins.str"],"extra_attrs":null,"type_ref":"builtins.tuple"}},"values":[],"variance":0},"type_guard":null,"type_is":null,"unpack_kwargs":false,"variables":[{".class":"TypeVarType","default":{".class":"AnyType","missing_import_name":null,"source_any":null,"type_of_any":4},"fullname":"pyarrow.__lib_pxi.config.RuntimeInfo._NT","id":-1,"name":"_NT","namespace":"pyarrow.__lib_pxi.config.RuntimeInfo._make","upper_bound":{".class":"TupleType","implicit":false,"items":["builtins.str","builtins.str"],"partial_fallback":{".class":"Instance","args":["builtins.str"],"extra_attrs":null,"type_ref":"builtins.tuple"}},"values":[],"variance":0}]}},"is_overload":false,"var":{".class":"Var","flags":["is_classmethod","is_ready"],"fullname":"pyarrow.__lib_pxi.config.RuntimeInfo._make","name":"_make","setter_type":null,"type":{".class":"CallableType","arg_kinds":[0,0],"arg_names":["_cls","iterable"],"arg_types":[{".class":"TypeType","is_type_form":false,"item":{".class":"TypeVarType","default":{".class":"AnyType","missing_import_name":null,"source_any":null,"type_of_any":4},"fullname":"pyarrow.__lib_pxi.config.RuntimeInfo._NT","id":-1,"name":"_NT","namespace":"pyarrow.__lib_pxi.config.RuntimeInfo._make","upper_bound":{".class":"TupleType","implicit":false,"items":["builtins.str","builtins.str"],"partial_fallback":{".class":"Instance","args":["builtins.str"],"extra_attrs":null,"type_ref":"builtins.tuple"}},"values":[],"variance":0}},{".class":"Instance","args":[{".class":"AnyType","missing_import_name":null,"source_any":null,"type_of_any":6}],"extra_attrs":null,"type_ref":"typing.Iterable"}],"fallback":"builtins.function","from_concatenate":false,"implicit":false,"imprecise_arg_kinds":false,"is_bound":false,"is_ellipsis_args":false,"name":"_make of RuntimeInfo","ret_type":{".class":"TypeVarType","default":{".class":"AnyType","missing_import_name":null,"source_any":null,"type_of_any":4},"fullname":"pyarrow.__lib_pxi.config.RuntimeInfo._NT","id":-1,"name":"_NT","namespace":"pyarrow.__lib_pxi.config.RuntimeInfo._make","upper_bound":{".class":"TupleType","implicit":false,"items":["builtins.str","builtins.str"],"partial_fallback":{".class":"Instance","args":["builtins.str"],"extra_attrs":null,"type_ref":"builtins.tuple"}},"values":[],"variance":0},"type_guard":null,"type_is":null,"unpack_kwargs":false,"variables":[{".class":"TypeVarType","default":{".class":"AnyType","missing_import_name":null,"source_any":null,"type_of_any":4},"fullname":"pyarrow.__lib_pxi.config.RuntimeInfo._NT","id":-1,"name":"_NT","namespace":"pyarrow.__lib_pxi.config.RuntimeInfo._make","upper_bound":{".class":"TupleType","implicit":false,"items":["builtins.str","builtins.str"],"partial_fallback":{".class":"Instance","args":["builtins.str"],"extra_attrs":null,"type_ref":"builtins.tuple"}},"values":[],"variance":0}]}}},"plugin_generated":true},"_replace":{".class":"SymbolTableNode","kind":"Mdef","node":{".class":"FuncDef","abstract_status":0,"arg_kinds":[0,5,5],"arg_names":["_self","simd_level","detected_simd_level"],"dataclass_transform_spec":null,"deprecated":null,"flags":[],"fullname":"pyarrow.__lib_pxi.config.RuntimeInfo._replace","name":"_replace","original_first_arg":"_self","type":{".class":"CallableType","arg_kinds":[0,5,5],"arg_names":["_self","simd_level","detected_simd_level"],"arg_types":[{".class":"TypeVarType","default":{".class":"AnyType","missing_import_name":null,"source_any":null,"type_of_any":4},"fullname":"pyarrow.__lib_pxi.config.RuntimeInfo._NT","id":-1,"name":"_NT","namespace":"pyarrow.__lib_pxi.config.RuntimeInfo._replace","upper_bound":{".class":"TupleType","implicit":false,"items":["builtins.str","builtins.str"],"partial_fallback":{".class":"Instance","args":["builtins.str"],"extra_attrs":null,"type_ref":"builtins.tuple"}},"values":[],"variance":0},"builtins.str","builtins.str"],"fallback":"builtins.function","from_concatenate":false,"implicit":false,"imprecise_arg_kinds":false,"is_bound":false,"is_ellipsis_args":false,"name":"_replace of RuntimeInfo","ret_type":{".class":"TypeVarType","default":{".class":"AnyType","missing_import_name":null,"source_any":null,"type_of_any":4},"fullname":"pyarrow.__lib_pxi.config.RuntimeInfo._NT","id":-1,"name":"_NT","namespace":"pyarrow.__lib_pxi.config.RuntimeInfo._replace","upper_bound":{".class":"TupleType","implicit":false,"items":["builtins.str","builtins.str"],"partial_fallback":{".class":"Instance","args":["builtins.str"],"extra_attrs":null,"type_ref":"builtins.tuple"}},"values":[],"variance":0},"type_guard":null,"type_is":null,"unpack_kwargs":false,"variables":[{".class":"TypeVarType","default":{".class":"AnyType","missing_import_name":null,"source_any":null,"type_of_any":4},"fullname":"pyarrow.__lib_pxi.config.RuntimeInfo._NT","id":-1,"name":"_NT","namespace":"pyarrow.__lib_pxi.config.RuntimeInfo._replace","upper_bound":{".class":"TupleType","implicit":false,"items":["builtins.str","builtins.str"],"partial_fallback":{".class":"Instance","args":["builtins.str"],"extra_attrs":null,"type_ref":"builtins.tuple"}},"values":[],"variance":0}]}},"plugin_generated":true},"_source":{".class":"SymbolTableNode","kind":"Mdef","node":{".class":"Var","flags":["is_initialized_in_class","is_ready"],"fullname":"pyarrow.__lib_pxi.config.RuntimeInfo._source","name":"_source","setter_type":null,"type":"builtins.str"}},"detected_simd_level":{".class":"SymbolTableNode","kind":"Mdef","node":{".class":"Var","flags":["is_property","is_ready"],"fullname":"pyarrow.__lib_pxi.config.RuntimeInfo.detected_simd_level","name":"detected_simd_level","setter_type":null,"type":"builtins.str"}},"detected_simd_level-redefinition":{".class":"SymbolTableNode","cross_ref":"pyarrow.__lib_pxi.config.RuntimeInfo.detected_simd_level","kind":"Mdef"},"simd_level":{".class":"SymbolTableNode","kind":"Mdef","node":{".class":"Var","flags":["is_property","is_ready"],"fullname":"pyarrow.__lib_pxi.config.RuntimeInfo.simd_level","name":"simd_level","setter_type":null,"type":"builtins.str"}},"simd_level-redefinition":{".class":"SymbolTableNode","cross_ref":"pyarrow.__lib_pxi.config.RuntimeInfo.simd_level","kind":"Mdef"}},"self_type":{".class":"TypeVarType","default":{".class":"AnyType","missing_import_name":null,"source_any":null,"type_of_any":4},"fullname":"pyarrow.__lib_pxi.config.RuntimeInfo.Self","id":0,"name":"Self","namespace":"","upper_bound":{".class":"TupleType","implicit":false,"items":["builtins.str","builtins.str"],"partial_fallback":"pyarrow.__lib_pxi.config.RuntimeInfo"},"values":[],"variance":0},"slots":null,"tuple_type":{".class":"TupleType","implicit":false,"items":["builtins.str","builtins.str"],"partial_fallback":{".class":"Instance","args":["builtins.str"],"extra_attrs":null,"type_ref":"builtins.tuple"}},"type_vars":[],"typeddict_type":null}},"VersionInfo":{".class":"SymbolTableNode","kind":"Gdef","node":{".class":"TypeInfo","_promote":[],"abstract_attributes":[],"alt_promote":null,"bases":[{".class":"Instance","args":["builtins.int"],"extra_attrs":null,"type_ref":"builtins.tuple"}],"dataclass_transform_spec":null,"declared_metaclass":null,"defn":{".class":"ClassDef","fullname":"pyarrow.__lib_pxi.config.VersionInfo","name":"VersionInfo","type_vars":[]},"deletable_attributes":[],"deprecated":null,"flags":["is_named_tuple"],"fullname":"pyarrow.__lib_pxi.config.VersionInfo","has_param_spec_type":false,"metaclass_type":null,"metadata":{"namedtuple":{"fields":["major","minor","patch"]}},"module_name":"pyarrow.__lib_pxi.config","mro":["pyarrow.__lib_pxi.config.VersionInfo","builtins.tuple","typing.Sequence","typing.Reversible","typing.Collection","typing.Iterable","typing.Container","builtins.object"],"names":{".class":"SymbolTable","_NT":{".class":"SymbolTableNode","kind":"Mdef","node":{".class":"TypeVarExpr","default":{".class":"AnyType","missing_import_name":null,"source_any":null,"type_of_any":4},"fullname":"pyarrow.__lib_pxi.config.VersionInfo._NT","name":"_NT","upper_bound":{".class":"TupleType","implicit":false,"items":["builtins.int","builtins.int","builtins.int"],"partial_fallback":{".class":"Instance","args":["builtins.int"],"extra_attrs":null,"type_ref":"builtins.tuple"}},"values":[],"variance":0}},"__annotations__":{".class":"SymbolTableNode","kind":"Mdef","node":{".class":"Var","flags":["is_initialized_in_class","is_ready"],"fullname":"pyarrow.__lib_pxi.config.VersionInfo.__annotations__","name":"__annotations__","setter_type":null,"type":{".class":"Instance","args":["builtins.str",{".class":"AnyType","missing_import_name":null,"source_any":null,"type_of_any":6}],"extra_attrs":null,"type_ref":"builtins.dict"}}},"__doc__":{".class":"SymbolTableNode","kind":"Mdef","node":{".class":"Var","flags":["is_initialized_in_class","is_ready"],"fullname":"pyarrow.__lib_pxi.config.VersionInfo.__doc__","name":"__doc__","setter_type":null,"type":"builtins.str"}},"__match_args__":{".class":"SymbolTableNode","kind":"Mdef","node":{".class":"Var","flags":["is_initialized_in_class","is_ready"],"fullname":"pyarrow.__lib_pxi.config.VersionInfo.__match_args__","name":"__match_args__","setter_type":null,"type":{".class":"TupleType","implicit":false,"items":[{".class":"LiteralType","fallback":"builtins.str","value":"major"},{".class":"LiteralType","fallback":"builtins.str","value":"minor"},{".class":"LiteralType","fallback":"builtins.str","value":"patch"}],"partial_fallback":{".class":"Instance","args":[{".class":"AnyType","missing_import_name":null,"source_any":null,"type_of_any":6}],"extra_attrs":null,"type_ref":"builtins.tuple"}}}},"__new__":{".class":"SymbolTableNode","kind":"Mdef","node":{".class":"FuncDef","abstract_status":0,"arg_kinds":[0,0,0,0],"arg_names":["_cls","major","minor","patch"],"dataclass_transform_spec":null,"deprecated":null,"flags":["is_static"],"fullname":"pyarrow.__lib_pxi.config.VersionInfo.__new__","name":"__new__","original_first_arg":"_cls","type":{".class":"CallableType","arg_kinds":[0,0,0,0],"arg_names":["_cls","major","minor","patch"],"arg_types":[{".class":"TypeType","is_type_form":false,"item":{".class":"TypeVarType","default":{".class":"AnyType","missing_import_name":null,"source_any":null,"type_of_any":4},"fullname":"pyarrow.__lib_pxi.config.VersionInfo._NT","id":-1,"name":"_NT","namespace":"pyarrow.__lib_pxi.config.VersionInfo.__new__","upper_bound":{".class":"TupleType","implicit":false,"items":["builtins.int","builtins.int","builtins.int"],"partial_fallback":{".class":"Instance","args":["builtins.int"],"extra_attrs":null,"type_ref":"builtins.tuple"}},"values":[],"variance":0}},"builtins.int","builtins.int","builtins.int"],"fallback":"builtins.function","from_concatenate":false,"implicit":false,"imprecise_arg_kinds":false,"is_bound":false,"is_ellipsis_args":false,"name":"__new__ of VersionInfo","ret_type":{".class":"TypeVarType","default":{".class":"AnyType","missing_import_name":null,"source_any":null,"type_of_any":4},"fullname":"pyarrow.__lib_pxi.config.VersionInfo._NT","id":-1,"name":"_NT","namespace":"pyarrow.__lib_pxi.config.VersionInfo.__new__","upper_bound":{".class":"TupleType","implicit":false,"items":["builtins.int","builtins.int","builtins.int"],"partial_fallback":{".class":"Instance","args":["builtins.int"],"extra_attrs":null,"type_ref":"builtins.tuple"}},"values":[],"variance":0},"type_guard":null,"type_is":null,"unpack_kwargs":false,"variables":[{".class":"TypeVarType","default":{".class":"AnyType","missing_import_name":null,"source_any":null,"type_of_any":4},"fullname":"pyarrow.__lib_pxi.config.VersionInfo._NT","id":-1,"name":"_NT","namespace":"pyarrow.__lib_pxi.config.VersionInfo.__new__","upper_bound":{".class":"TupleType","implicit":false,"items":["builtins.int","builtins.int","builtins.int"],"partial_fallback":{".class":"Instance","args":["builtins.int"],"extra_attrs":null,"type_ref":"builtins.tuple"}},"values":[],"variance":0}]}},"plugin_generated":true},"__replace__":{".class":"SymbolTableNode","kind":"Mdef","node":{".class":"FuncDef","abstract_status":0,"arg_kinds":[0,5,5,5],"arg_names":["_self","major","minor","patch"],"dataclass_transform_spec":null,"deprecated":null,"flags":[],"fullname":"pyarrow.__lib_pxi.config.VersionInfo.__replace__","name":"__replace__","original_first_arg":"_self","type":{".class":"CallableType","arg_kinds":[0,5,5,5],"arg_names":["_self","major","minor","patch"],"arg_types":[{".class":"TypeVarType","default":{".class":"AnyType","missing_import_name":null,"source_any":null,"type_of_any":4},"fullname":"pyarrow.__lib_pxi.config.VersionInfo._NT","id":-1,"name":"_NT","namespace":"pyarrow.__lib_pxi.config.VersionInfo.__replace__","upper_bound":{".class":"TupleType","implicit":false,"items":["builtins.int","builtins.int","builtins.int"],"partial_fallback":{".class":"Instance","args":["builtins.int"],"extra_attrs":null,"type_ref":"builtins.tuple"}},"values":[],"variance":0},"builtins.int","builtins.int","builtins.int"],"fallback":"builtins.function","from_concatenate":false,"implicit":false,"imprecise_arg_kinds":false,"is_bound":false,"is_ellipsis_args":false,"name":"__replace__ of VersionInfo","ret_type":{".class":"TypeVarType","default":{".class":"AnyType","missing_import_name":null,"source_any":null,"type_of_any":4},"fullname":"pyarrow.__lib_pxi.config.VersionInfo._NT","id":-1,"name":"_NT","namespace":"pyarrow.__lib_pxi.config.VersionInfo.__replace__","upper_bound":{".class":"TupleType","implicit":false,"items":["builtins.int","builtins.int","builtins.int"],"partial_fallback":{".class":"Instance","args":["builtins.int"],"extra_attrs":null,"type_ref":"builtins.tuple"}},"values":[],"variance":0},"type_guard":null,"type_is":null,"unpack_kwargs":false,"variables":[{".class":"TypeVarType","default":{".class":"AnyType","missing_import_name":null,"source_any":null,"type_of_any":4},"fullname":"pyarrow.__lib_pxi.config.VersionInfo._NT","id":-1,"name":"_NT","namespace":"pyarrow.__lib_pxi.config.VersionInfo.__replace__","upper_bound":{".class":"TupleType","implicit":false,"items":["builtins.int","builtins.int","builtins.int"],"partial_fallback":{".class":"Instance","args":["builtins.int"],"extra_attrs":null,"type_ref":"builtins.tuple"}},"values":[],"variance":0}]}},"plugin_generated":true},"_asdict":{".class":"SymbolTableNode","kind":"Mdef","node":{".class":"FuncDef","abstract_status":0,"arg_kinds":[0],"arg_names":["_self"],"dataclass_transform_spec":null,"deprecated":null,"flags":[],"fullname":"pyarrow.__lib_pxi.config.VersionInfo._asdict","name":"_asdict","original_first_arg":"_self","type":{".class":"CallableType","arg_kinds":[0],"arg_names":["_self"],"arg_types":[{".class":"TypeVarType","default":{".class":"AnyType","missing_import_name":null,"source_any":null,"type_of_any":4},"fullname":"pyarrow.__lib_pxi.config.VersionInfo._NT","id":-1,"name":"_NT","namespace":"pyarrow.__lib_pxi.config.VersionInfo._asdict","upper_bound":{".class":"TupleType","implicit":false,"items":["builtins.int","builtins.int","builtins.int"],"partial_fallback":{".class":"Instance","args":["builtins.int"],"extra_attrs":null,"type_ref":"builtins.tuple"}},"values":[],"variance":0}],"fallback":"builtins.function","from_concatenate":false,"implicit":false,"imprecise_arg_kinds":false,"is_bound":false,"is_ellipsis_args":false,"name":"_asdict of VersionInfo","ret_type":{".class":"Instance","args":["builtins.str",{".class":"AnyType","missing_import_name":null,"source_any":null,"type_of_any":6}],"extra_attrs":null,"type_ref":"builtins.dict"},"type_guard":null,"type_is":null,"unpack_kwargs":false,"variables":[{".class":"TypeVarType","default":{".class":"AnyType","missing_import_name":null,"source_any":null,"type_of_any":4},"fullname":"pyarrow.__lib_pxi.config.VersionInfo._NT","id":-1,"name":"_NT","namespace":"pyarrow.__lib_pxi.config.VersionInfo._asdict","upper_bound":{".class":"TupleType","implicit":false,"items":["builtins.int","builtins.int","builtins.int"],"partial_fallback":{".class":"Instance","args":["builtins.int"],"extra_attrs":null,"type_ref":"builtins.tuple"}},"values":[],"variance":0}]}},"plugin_generated":true},"_field_defaults":{".class":"SymbolTableNode","kind":"Mdef","node":{".class":"Var","flags":["is_initialized_in_class","is_ready"],"fullname":"pyarrow.__lib_pxi.config.VersionInfo._field_defaults","name":"_field_defaults","setter_type":null,"type":{".class":"Instance","args":["builtins.str",{".class":"AnyType","missing_import_name":null,"source_any":null,"type_of_any":6}],"extra_attrs":null,"type_ref":"builtins.dict"}}},"_field_types":{".class":"SymbolTableNode","kind":"Mdef","node":{".class":"Var","flags":["is_initialized_in_class","is_ready"],"fullname":"pyarrow.__lib_pxi.config.VersionInfo._field_types","name":"_field_types","setter_type":null,"type":{".class":"Instance","args":["builtins.str",{".class":"AnyType","missing_import_name":null,"source_any":null,"type_of_any":6}],"extra_attrs":null,"type_ref":"builtins.dict"}}},"_fields":{".class":"SymbolTableNode","kind":"Mdef","node":{".class":"Var","flags":["is_initialized_in_class","is_ready"],"fullname":"pyarrow.__lib_pxi.config.VersionInfo._fields","name":"_fields","setter_type":null,"type":{".class":"TupleType","implicit":false,"items":["builtins.str","builtins.str","builtins.str"],"partial_fallback":{".class":"Instance","args":[{".class":"AnyType","missing_import_name":null,"source_any":null,"type_of_any":6}],"extra_attrs":null,"type_ref":"builtins.tuple"}}}},"_make":{".class":"SymbolTableNode","kind":"Mdef","node":{".class":"Decorator","func":{".class":"FuncDef","abstract_status":0,"arg_kinds":[0,0],"arg_names":["_cls","iterable"],"dataclass_transform_spec":null,"deprecated":null,"flags":["is_class","is_decorated"],"fullname":"pyarrow.__lib_pxi.config.VersionInfo._make","name":"_make","original_first_arg":"_cls","type":{".class":"CallableType","arg_kinds":[0,0],"arg_names":["_cls","iterable"],"arg_types":[{".class":"TypeType","is_type_form":false,"item":{".class":"TypeVarType","default":{".class":"AnyType","missing_import_name":null,"source_any":null,"type_of_any":4},"fullname":"pyarrow.__lib_pxi.config.VersionInfo._NT","id":-1,"name":"_NT","namespace":"pyarrow.__lib_pxi.config.VersionInfo._make","upper_bound":{".class":"TupleType","implicit":false,"items":["builtins.int","builtins.int","builtins.int"],"partial_fallback":{".class":"Instance","args":["builtins.int"],"extra_attrs":null,"type_ref":"builtins.tuple"}},"values":[],"variance":0}},{".class":"Instance","args":[{".class":"AnyType","missing_import_name":null,"source_any":null,"type_of_any":6}],"extra_attrs":null,"type_ref":"typing.Iterable"}],"fallback":"builtins.function","from_concatenate":false,"implicit":false,"imprecise_arg_kinds":false,"is_bound":false,"is_ellipsis_args":false,"name":"_make of VersionInfo","ret_type":{".class":"TypeVarType","default":{".class":"AnyType","missing_import_name":null,"source_any":null,"type_of_any":4},"fullname":"pyarrow.__lib_pxi.config.VersionInfo._NT","id":-1,"name":"_NT","namespace":"pyarrow.__lib_pxi.config.VersionInfo._make","upper_bound":{".class":"TupleType","implicit":false,"items":["builtins.int","builtins.int","builtins.int"],"partial_fallback":{".class":"Instance","args":["builtins.int"],"extra_attrs":null,"type_ref":"builtins.tuple"}},"values":[],"variance":0},"type_guard":null,"type_is":null,"unpack_kwargs":false,"variables":[{".class":"TypeVarType","default":{".class":"AnyType","missing_import_name":null,"source_any":null,"type_of_any":4},"fullname":"pyarrow.__lib_pxi.config.VersionInfo._NT","id":-1,"name":"_NT","namespace":"pyarrow.__lib_pxi.config.VersionInfo._make","upper_bound":{".class":"TupleType","implicit":false,"items":["builtins.int","builtins.int","builtins.int"],"partial_fallback":{".class":"Instance","args":["builtins.int"],"extra_attrs":null,"type_ref":"builtins.tuple"}},"values":[],"variance":0}]}},"is_overload":false,"var":{".class":"Var","flags":["is_classmethod","is_ready"],"fullname":"pyarrow.__lib_pxi.config.VersionInfo._make","name":"_make","setter_type":null,"type":{".class":"CallableType","arg_kinds":[0,0],"arg_names":["_cls","iterable"],"arg_types":[{".class":"TypeType","is_type_form":false,"item":{".class":"TypeVarType","default":{".class":"AnyType","missing_import_name":null,"source_any":null,"type_of_any":4},"fullname":"pyarrow.__lib_pxi.config.VersionInfo._NT","id":-1,"name":"_NT","namespace":"pyarrow.__lib_pxi.config.VersionInfo._make","upper_bound":{".class":"TupleType","implicit":false,"items":["builtins.int","builtins.int","builtins.int"],"partial_fallback":{".class":"Instance","args":["builtins.int"],"extra_attrs":null,"type_ref":"builtins.tuple"}},"values":[],"variance":0}},{".class":"Instance","args":[{".class":"AnyType","missing_import_name":null,"source_any":null,"type_of_any":6}],"extra_attrs":null,"type_ref":"typing.Iterable"}],"fallback":"builtins.function","from_concatenate":false,"implicit":false,"imprecise_arg_kinds":false,"is_bound":false,"is_ellipsis_args":false,"name":"_make of VersionInfo","ret_type":{".class":"TypeVarType","default":{".class":"AnyType","missing_import_name":null,"source_any":null,"type_of_any":4},"fullname":"pyarrow.__lib_pxi.config.VersionInfo._NT","id":-1,"name":"_NT","namespace":"pyarrow.__lib_pxi.config.VersionInfo._make","upper_bound":{".class":"TupleType","implicit":false,"items":["builtins.int","builtins.int","builtins.int"],"partial_fallback":{".class":"Instance","args":["builtins.int"],"extra_attrs":null,"type_ref":"builtins.tuple"}},"values":[],"variance":0},"type_guard":null,"type_is":null,"unpack_kwargs":false,"variables":[{".class":"TypeVarType","default":{".class":"AnyType","missing_import_name":null,"source_any":null,"type_of_any":4},"fullname":"pyarrow.__lib_pxi.config.VersionInfo._NT","id":-1,"name":"_NT","namespace":"pyarrow.__lib_pxi.config.VersionInfo._make","upper_bound":{".class":"TupleType","implicit":false,"items":["builtins.int","builtins.int","builtins.int"],"partial_fallback":{".class":"Instance","args":["builtins.int"],"extra_attrs":null,"type_ref":"builtins.tuple"}},"values":[],"variance":0}]}}},"plugin_generated":true},"_replace":{".class":"SymbolTableNode","kind":"Mdef","node":{".class":"FuncDef","abstract_status":0,"arg_kinds":[0,5,5,5],"arg_names":["_self","major","minor","patch"],"dataclass_transform_spec":null,"deprecated":null,"flags":[],"fullname":"pyarrow.__lib_pxi.config.VersionInfo._replace","name":"_replace","original_first_arg":"_self","type":{".class":"CallableType","arg_kinds":[0,5,5,5],"arg_names":["_self","major","minor","patch"],"arg_types":[{".class":"TypeVarType","default":{".class":"AnyType","missing_import_name":null,"source_any":null,"type_of_any":4},"fullname":"pyarrow.__lib_pxi.config.VersionInfo._NT","id":-1,"name":"_NT","namespace":"pyarrow.__lib_pxi.config.VersionInfo._replace","upper_bound":{".class":"TupleType","implicit":false,"items":["builtins.int","builtins.int","builtins.int"],"partial_fallback":{".class":"Instance","args":["builtins.int"],"extra_attrs":null,"type_ref":"builtins.tuple"}},"values":[],"variance":0},"builtins.int","builtins.int","builtins.int"],"fallback":"builtins.function","from_concatenate":false,"implicit":false,"imprecise_arg_kinds":false,"is_bound":false,"is_ellipsis_args":false,"name":"_replace of VersionInfo","ret_type":{".class":"TypeVarType","default":{".class":"AnyType","missing_import_name":null,"source_any":null,"type_of_any":4},"fullname":"pyarrow.__lib_pxi.config.VersionInfo._NT","id":-1,"name":"_NT","namespace":"pyarrow.__lib_pxi.config.VersionInfo._replace","upper_bound":{".class":"TupleType","implicit":false,"items":["builtins.int","builtins.int","builtins.int"],"partial_fallback":{".class":"Instance","args":["builtins.int"],"extra_attrs":null,"type_ref":"builtins.tuple"}},"values":[],"variance":0},"type_guard":null,"type_is":null,"unpack_kwargs":false,"variables":[{".class":"TypeVarType","default":{".class":"AnyType","missing_import_name":null,"source_any":null,"type_of_any":4},"fullname":"pyarrow.__lib_pxi.config.VersionInfo._NT","id":-1,"name":"_NT","namespace":"pyarrow.__lib_pxi.config.VersionInfo._replace","upper_bound":{".class":"TupleType","implicit":false,"items":["builtins.int","builtins.int","builtins.int"],"partial_fallback":{".class":"Instance","args":["builtins.int"],"extra_attrs":null,"type_ref":"builtins.tuple"}},"values":[],"variance":0}]}},"plugin_generated":true},"_source":{".class":"SymbolTableNode","kind":"Mdef","node":{".class":"Var","flags":["is_initialized_in_class","is_ready"],"fullname":"pyarrow.__lib_pxi.config.VersionInfo._source","name":"_source","setter_type":null,"type":"builtins.str"}},"major":{".class":"SymbolTableNode","kind":"Mdef","node":{".class":"Var","flags":["is_property","is_ready"],"fullname":"pyarrow.__lib_pxi.config.VersionInfo.major","name":"major","setter_type":null,"type":"builtins.int"}},"major-redefinition":{".class":"SymbolTableNode","cross_ref":"pyarrow.__lib_pxi.config.VersionInfo.major","kind":"Mdef"},"minor":{".class":"SymbolTableNode","kind":"Mdef","node":{".class":"Var","flags":["is_property","is_ready"],"fullname":"pyarrow.__lib_pxi.config.VersionInfo.minor","name":"minor","setter_type":null,"type":"builtins.int"}},"minor-redefinition":{".class":"SymbolTableNode","cross_ref":"pyarrow.__lib_pxi.config.VersionInfo.minor","kind":"Mdef"},"patch":{".class":"SymbolTableNode","kind":"Mdef","node":{".class":"Var","flags":["is_property","is_ready"],"fullname":"pyarrow.__lib_pxi.config.VersionInfo.patch","name":"patch","setter_type":null,"type":"builtins.int"}},"patch-redefinition":{".class":"SymbolTableNode","cross_ref":"pyarrow.__lib_pxi.config.VersionInfo.patch","kind":"Mdef"}},"self_type":{".class":"TypeVarType","default":{".class":"AnyType","missing_import_name":null,"source_any":null,"type_of_any":4},"fullname":"pyarrow.__lib_pxi.config.VersionInfo.Self","id":0,"name":"Self","namespace":"","upper_bound":{".class":"TupleType","implicit":false,"items":["builtins.int","builtins.int","builtins.int"],"partial_fallback":"pyarrow.__lib_pxi.config.VersionInfo"},"values":[],"variance":0},"slots":null,"tuple_type":{".class":"TupleType","implicit":false,"items":["builtins.int","builtins.int","builtins.int"],"partial_fallback":{".class":"Instance","args":["builtins.int"],"extra_attrs":null,"type_ref":"builtins.tuple"}},"type_vars":[],"typeddict_type":null}},"__all__":{".class":"SymbolTableNode","kind":"Gdef","module_public":false,"node":{".class":"Var","flags":["is_ready","is_inferred","has_explicit_value"],"fullname":"pyarrow.__lib_pxi.config.__all__","name":"__all__","setter_type":null,"type":{".class":"Instance","args":["builtins.str"],"extra_attrs":null,"type_ref":"builtins.list"}}},"__annotations__":{".class":"SymbolTableNode","kind":"Gdef","module_public":false,"node":{".class":"Var","flags":["is_ready"],"fullname":"pyarrow.__lib_pxi.config.__annotations__","name":"__annotations__","setter_type":null,"type":{".class":"Instance","args":["builtins.str",{".class":"AnyType","missing_import_name":null,"source_any":null,"type_of_any":6}],"extra_attrs":null,"type_ref":"builtins.dict"}}},"__doc__":{".class":"SymbolTableNode","kind":"Gdef","module_public":false,"node":{".class":"Var","flags":["is_ready"],"fullname":"pyarrow.__lib_pxi.config.__doc__","name":"__doc__","setter_type":null,"type":"builtins.str"}},"__file__":{".class":"SymbolTableNode","kind":"Gdef","module_public":false,"node":{".class":"Var","flags":["is_ready"],"fullname":"pyarrow.__lib_pxi.config.__file__","name":"__file__","setter_type":null,"type":"builtins.str"}},"__name__":{".class":"SymbolTableNode","kind":"Gdef","module_public":false,"node":{".class":"Var","flags":["is_ready"],"fullname":"pyarrow.__lib_pxi.config.__name__","name":"__name__","setter_type":null,"type":"builtins.str"}},"__package__":{".class":"SymbolTableNode","kind":"Gdef","module_public":false,"node":{".class":"Var","flags":["is_ready"],"fullname":"pyarrow.__lib_pxi.config.__package__","name":"__package__","setter_type":null,"type":"builtins.str"}},"__spec__":{".class":"SymbolTableNode","kind":"Gdef","module_public":false,"node":{".class":"Var","flags":["is_ready"],"fullname":"pyarrow.__lib_pxi.config.__spec__","name":"__spec__","setter_type":null,"type":"_frozen_importlib.ModuleSpec"}},"cpp_build_info":{".class":"SymbolTableNode","kind":"Gdef","node":{".class":"Var","flags":["is_ready"],"fullname":"pyarrow.__lib_pxi.config.cpp_build_info","name":"cpp_build_info","setter_type":null,"type":{".class":"TypeAliasType","args":[],"type_ref":"pyarrow.__lib_pxi.config.BuildInfo"}}},"cpp_version":{".class":"SymbolTableNode","kind":"Gdef","node":{".class":"Var","flags":["is_ready"],"fullname":"pyarrow.__lib_pxi.config.cpp_version","name":"cpp_version","setter_type":null,"type":"builtins.str"}},"cpp_version_info":{".class":"SymbolTableNode","kind":"Gdef","node":{".class":"Var","flags":["is_ready"],"fullname":"pyarrow.__lib_pxi.config.cpp_version_info","name":"cpp_version_info","setter_type":null,"type":{".class":"TypeAliasType","args":[],"type_ref":"pyarrow.__lib_pxi.config.VersionInfo"}}},"runtime_info":{".class":"SymbolTableNode","kind":"Gdef","node":{".class":"FuncDef","abstract_status":0,"arg_kinds":[],"arg_names":[],"dataclass_transform_spec":null,"deprecated":null,"flags":[],"fullname":"pyarrow.__lib_pxi.config.runtime_info","name":"runtime_info","original_first_arg":null,"type":{".class":"CallableType","arg_kinds":[],"arg_names":[],"arg_types":[],"fallback":"builtins.function","from_concatenate":false,"implicit":false,"imprecise_arg_kinds":false,"is_bound":false,"is_ellipsis_args":false,"name":"runtime_info","ret_type":{".class":"TypeAliasType","args":[],"type_ref":"pyarrow.__lib_pxi.config.RuntimeInfo"},"type_guard":null,"type_is":null,"unpack_kwargs":false,"variables":[]}}},"set_timezone_db_path":{".class":"SymbolTableNode","kind":"Gdef","node":{".class":"FuncDef","abstract_status":0,"arg_kinds":[0],"arg_names":["path"],"dataclass_transform_spec":null,"deprecated":null,"flags":[],"fullname":"pyarrow.__lib_pxi.config.set_timezone_db_path","name":"set_timezone_db_path","original_first_arg":"path","type":{".class":"CallableType","arg_kinds":[0],"arg_names":["path"],"arg_types":["builtins.str"],"fallback":"builtins.function","from_concatenate":false,"implicit":false,"imprecise_arg_kinds":false,"is_bound":false,"is_ellipsis_args":false,"name":"set_timezone_db_path","ret_type":{".class":"NoneType"},"type_guard":null,"type_is":null,"unpack_kwargs":false,"variables":[]}}}},"path":"/home/marlonsc/flext/.venv/lib/python3.13/site-packages/pyarrow-stubs/__lib_pxi/config.pyi"}